kami_filemanager/__init__.py
kami_filemanager/filemanager.py
kami_filemanager-0.1.0.dist-info/LICENSE
kami_filemanager-0.1.0.dist-info/METADATA
kami_filemanager-0.1.0.dist-info/WHEEL
kami_filemanager-0.1.0.dist-info/RECORD
